tipsql/sqlite3/__init__.py
tipsql/sqlite3/connection.py
tipsql/sqlite3/cursor.py
tipsql/sqlite3/datatypes.py
tipsql/sqlite3/plugin.py
tipsql/sqlite3/query/__init__.py
tipsql/sqlite3/query/builder.py
tipsql_sqlite3-0.0.14.dist-info/METADATA
tipsql_sqlite3-0.0.14.dist-info/WHEEL
tipsql_sqlite3-0.0.14.dist-info/entry_points.txt
tipsql_sqlite3-0.0.14.dist-info/RECORD
