Metadata-Version: 2.1
Name: tipsql-sqlite3
Version: 0.0.14
Summary: tipsql adapter for sqlite3
Author: yassun7010
Author-email: yassun7010@outlook.com
Requires-Python: >=3.12,<4.0
Classifier: Programming Language :: Python :: 3
Classifier: Programming Language :: Python :: 3.12
Requires-Dist: tipsql-core (==0.0.14)
Requires-Dist: typing-extensions (>=4.8.0,<5.0.0)
